{
    "resources": [
        {
            "type": "lambda",
            "provider": "aws",
            "id": "lambdahost"
        }
    ],
    "global_tags": {
        "dxDeployedBy": "Alec",
        "dxProduct": "V3",
        "dxDepartment": "product",
        "dxEnvironment": "development",
        "dxOwningTeam": "Demotron"
    },
    "services": [
        {
            "destinations": [
                "lambdahost"
            ],
            "deploy_script_path": "deploy/lambda/roles",
            "source_repository": "-b nerdpack-course-static-api https://github.com/newrelic/demo-pythontron.git",
            "display_name": "Static API",
            "id": "staticapi"
        }
    ]
}
